sharebook/__init__.py
sharebook/version.py
sharebook-0.0.1.dist-info/METADATA
sharebook-0.0.1.dist-info/WHEEL
sharebook-0.0.1.dist-info/top_level.txt
sharebook-0.0.1.dist-info/RECORD
