Metadata-Version: 2.1
Name: sharebook
Version: 0.0.1
Summary: Sharebook
Home-page: UNKNOWN
Author: Datalayer
Author-email: eric@datalayer.io
License: MIT
Project-URL: Source, https://github.com/datalayer/sharebook
Project-URL: Tracker, https://github.com/datalayer/sharebook/issues
Keywords: jupyter admin
Platform: Linux
Platform: Mac OS X
Classifier: Intended Audience :: Developers
Classifier: Intended Audience :: System Administrators
Classifier: Intended Audience :: Science/Research
Classifier: License :: OSI Approved :: BSD License
Classifier: Programming Language :: Python
Classifier: Programming Language :: Python :: 3
Requires-Python: >=3.8
Requires-Dist: alembic
Requires-Dist: jupyterhub (>=1.4.1)
Requires-Dist: pluggy
Requires-Dist: tornado (>=6.0.4)
Requires-Dist: traitlets
